hspcore/__init__.py
hspcore/src/__init__.py
hspcore/src/hsp.py
hspcore-1.3.dist-info/LICENSE.txt
hspcore-1.3.dist-info/METADATA
hspcore-1.3.dist-info/WHEEL
hspcore-1.3.dist-info/top_level.txt
hspcore-1.3.dist-info/RECORD
