Metadata-Version: 2.1
Name: hspcore
Version: 1.3
Summary: Hansen Solubility Parameters (HSP) core functions.
Home-page: https://github.com/Gnpd/hspcore
Download-URL: https://github.com/Gnpd/hspcore/archive/refs/tags/v_1.3.tar.gz
Author: Alejandro Gutierrez
Author-email: a.gutierrez@g-npd.com
License: MIT
Keywords: HSP,Solubility
Classifier: Development Status :: 3 - Alpha
Classifier: Intended Audience :: Developers
Classifier: Topic :: Software Development :: Build Tools
Classifier: License :: OSI Approved :: MIT License
Classifier: Programming Language :: Python :: 3.11
Requires-Python: >=3.6
License-File: LICENSE.txt
Requires-Dist: scipy
